dj_db_rotated_secret/__init__.py
dj_db_rotated_secret/db_rotated_secret.py
dj_db_rotated_secret/settings.py
dj_db_rotated_secret-0.1.1.dist-info/LICENSE
dj_db_rotated_secret-0.1.1.dist-info/METADATA
dj_db_rotated_secret-0.1.1.dist-info/WHEEL
dj_db_rotated_secret-0.1.1.dist-info/RECORD
