Metadata-Version: 2.1
Name: dj-db-rotated-secret
Version: 0.1.1
Summary: AWS Secrets has a auto-rotation feature, but Django doesn't support it out of the box. This package provides a way to rotate the secret in Django settings.
Author: Justin Louie
Author-email: 224840+nitsujri@users.noreply.github.com
Requires-Python: >=3.10
Classifier: Programming Language :: Python :: 3
Classifier: Programming Language :: Python :: 3.10
Classifier: Programming Language :: Python :: 3.11
Classifier: Programming Language :: Python :: 3.12
Requires-Dist: django (>=4.0)
Project-URL: Homepage, https://github.com/jenfi-eng/dj-db-rotated-secret
Project-URL: Issues, https://github.com/jenfi-eng/dj-db-rotated-secret/issues
